Workbook
Name Categoria_que_mais_lucrou: Analise!$B$6
Name Faturamento_Casa: Analise!$I$21:$J$24
Name Faturamento_Eletrodomestico: Analise!$I$10:$J$13
Name Faturamento_Mensal: Analise!$D$2:$I$8
Name Faturamento_por_categoria: Analise!$D$10:$E$13
Name Faturamento_por_produto: Analise!$D$15:$E$25
Name Faturamento_Roupa: Analise!$I$15:$J$19
Name Faturamento_Total: Analise!$B$3
Name Mês_que_mais_faturou: Analise!$B$12
Name Porcentagem_de_metas_atingidas: Analise!$B$15
Name Produto_que_mais_lucrou: Analise!$B$9

Sheet Dados_Brutos
A1: Data | B1: Produto | C1: Categoria | D1: Quantidade | E1: Preço Unitário | F1: Faturamento da Venda | G1: Forma de Pagamento
A2: 45841 | B2: Calça | C2: Roupa | D2: 1 | E2: 107.3 | F2: =D2*E2 -> 107.3 | G2: Boleto Bancário
A3: 45841 | B3: Air Fryer | C3: Eletrodoméstico | D3: 1 | E3: 378.8 | F3: =D3*E3 -> 378.8 | G3: Cartão de Crédito
A4: 45841 | B4: Moletom | C4: Roupa | D4: 1 | E4: 297.5 | F4: =D4*E4 -> 297.5 | G4: Cartão de Crédito
A5: 45842 | B5: Guarda-roupa | C5: Casa | D5: 1 | E5: 1749.22 | F5: =D5*E5 -> 1749.22 | G5: Boleto Bancário
A6: 45843 | B6: Camisa | C6: Roupa | D6: 1 | E6: 79.9 | F6: =D6*E6 -> 79.9 | G6: Cartão de Crédito
A7: 45845 | B7: Cama | C7: Casa | D7: 1 | E7: 2289 | F7: =D7*E7 -> 2289 | G7: Cartão de Crédito
A8: 45845 | B8: Camisa | C8: Roupa | D8: 2 | E8: 79.9 | F8: =D8*E8 -> 159.8 | G8: Boleto Bancário
A9: 45846 | B9: Air Fryer | C9: Eletrodoméstico | D9: 1 | E9: 378.8 | F9: =D9*E9 -> 378.8 | G9: Boleto Bancário
A10: 45847 | B10: Geladeira | C10: Eletrodoméstico | D10: 1 | E10: 1699 | F10: =D10*E10 -> 1699 | G10: Cartão de Crédito
A11: 45849 | B11: Bermuda | C11: Roupa | D11: 3 | E11: 54.99 | F11: =D11*E11 -> 164.97 | G11: Boleto Bancário
A12: 45850 | B12: Guarda-roupa | C12: Casa | D12: 1 | E12: 1749.22 | F12: =D12*E12 -> 1749.22 | G12: Boleto Bancário
A13: 45850 | B13: Camisa | C13: Roupa | D13: 3 | E13: 79.9 | F13: =D13*E13 -> 239.7 | G13: Boleto Bancário
... A122: 46022 | B122: Air Fryer | C122: Eletrodoméstico | D122: 4 | E122: 378.8 | F122: =D122*E122 -> 1515.2 | G122: Boleto Bancário

Sheet Tratamento
B2: Data | C2: Mês | D2: Produto | E2: Categoria | F2: Quantidade | G2: Preço Unitário | H2: Faturamento da Venda | I2: Forma de Pagamento
B3: 45841 | C3: =TEXT(B3,"Mmmm") -> julho | D3: Calça | E3: Roupa | F3: 1 | G3: 107.3 | H3: =F3*G3 -> 107.3 | I3: Boleto Bancário
B4: 45841 | C4: =TEXT(B4,"Mmmm") -> julho | D4: Air Fryer | E4: Eletrodoméstico | F4: 1 | G4: 378.8 | H4: =F4*G4 -> 378.8 | I4: Cartão de Crédito
B5: 45841 | C5: =TEXT(B5,"Mmmm") -> julho | D5: Moletom | E5: Roupa | F5: 1 | G5: 297.5 | H5: =F5*G5 -> 297.5 | I5: Cartão de Crédito
B6: 45842 | C6: =TEXT(B6,"Mmmm") -> julho | D6: Guarda-roupa | E6: Casa | F6: 1 | G6: 1749.22 | H6: =F6*G6 -> 1749.22 | I6: Boleto Bancário
B7: 45843 | C7: =TEXT(B7,"Mmmm") -> julho | D7: Camisa | E7: Roupa | F7: 1 | G7: 79.9 | H7: =F7*G7 -> 79.9 | I7: Cartão de Crédito
B8: 45845 | C8: =TEXT(B8,"Mmmm") -> julho | D8: Cama | E8: Casa | F8: 1 | G8: 2289 | H8: =F8*G8 -> 2289 | I8: Cartão de Crédito
B9: 45845 | C9: =TEXT(B9,"Mmmm") -> julho | D9: Camisa | E9: Roupa | F9: 2 | G9: 79.9 | H9: =F9*G9 -> 159.8 | I9: Boleto Bancário
B10: 45846 | C10: =TEXT(B10,"Mmmm") -> julho | D10: Air Fryer | E10: Eletrodoméstico | F10: 1 | G10: 378.8 | H10: =F10*G10 -> 378.8 | I10: Boleto Bancário
B11: 45847 | C11: =TEXT(B11,"Mmmm") -> julho | D11: Geladeira | E11: Eletrodoméstico | F11: 1 | G11: 1699 | H11: =F11*G11 -> 1699 | I11: Cartão de Crédito
B12: 45849 | C12: =TEXT(B12,"Mmmm") -> julho | D12: Bermuda | E12: Roupa | F12: 3 | G12: 54.99 | H12: =F12*G12 -> 164.97 | I12: Boleto Bancário
B13: 45850 | C13: =TEXT(B13,"Mmmm") -> julho | D13: Guarda-roupa | E13: Casa | F13: 1 | G13: 1749.22 | H13: =F13*G13 -> 1749.22 | I13: Boleto Bancário
B14: 45850 | C14: =TEXT(B14,"Mmmm") -> julho | D14: Camisa | E14: Roupa | F14: 3 | G14: 79.9 | H14: =F14*G14 -> 239.7 | I14: Boleto Bancário
... B123: 46022 | C123: =TEXT(B123,"Mmmm") -> dezembro | D123: Air Fryer | E123: Eletrodoméstico | F123: 4 | G123: 378.8 | H123: =F123*G123 -> 1515.2 | I123: Boleto Bancário

Sheet Analise
B2: Qual o faturamento total? | D2: Mês | E2: Meta Mensal | F2: Data Inicial do Mês | G2: Data Final do Mês | H2: Faturamento | I2: Bateu a meta mensal?
B3: =SUM(Tratamento!H:H) -> 118910.68 | D3: Julho | E3: 30000 | F3: >=01/07/2025 | G3: <=31/07/2025 | H3: =SUMIFS(Tratamento!H:H,Tratamento!B:B,F3,Tratamento!B:B,G3) -> 36134.97 | I3: =IF(H3>E3,"Sim","Não") -> Sim
D4: Agosto | E4: 10000 | F4: >=01/08/2025 | G4: <=31/08/2025 | H4: =SUMIFS(Tratamento!H:H,Tratamento!B:B,F4,Tratamento!B:B,G4) -> 7739.3 | I4: =IF(H4>E4,"Sim","Não") -> Não
B5: Qual categoria trouxe mais lucro? | D5: Setembro | E5: 15000 | F5: >=01/09/2025 | G5: <=30/09/2025 | H5: =SUMIFS(Tratamento!H:H,Tratamento!B:B,F5,Tratamento!B:B,G5) -> 15329.4 | I5: =IF(H5>E5,"Sim","Não") -> Sim
B6: → Casa | D6: Outubro | E6: 15000 | F6: >=01/10/2025 | G6: <=31/10/2025 | H6: =SUMIFS(Tratamento!H:H,Tratamento!B:B,F6,Tratamento!B:B,G6) -> 13309.32 | I6: =IF(H6>E6,"Sim","Não") -> Não
D7: Novembro | E7: 20000 | F7: >=01/11/2025 | G7: <=30/11/2025 | H7: =SUMIFS(Tratamento!H:H,Tratamento!B:B,F7,Tratamento!B:B,G7) -> 24120.88 | I7: =IF(H7>E7,"Sim","Não") -> Sim
B8: Qual produto trouxe mais lucro? | D8: Dezembro | E8: 25000 | F8: >=01/12/2025 | G8: <=31/12/2025 | H8: =SUMIFS(Tratamento!H:H,Tratamento!B:B,F8,Tratamento!B:B,G8) -> 22276.81 | I8: =IF(H8>E8,"Sim","Não") -> Não
B9: → Cama
D10: Categoria | E10: Faturamento | I10: Categoria "Eletrodoméstico" | J10: Preços
B11: Qual mês faturou mais? | D11: Casa | E11: =SUMIFS(Tratamento!H:H,Tratamento!E:E,D11) -> 56515.38 | I11: Geladeira | J11: 1699
B12: → Julho | D12: Eletrodoméstico | E12: =SUMIFS(Tratamento!H:H,Tratamento!E:E,D12) -> 48565.24 | I12: Microondas | J12: 677.87
D13: Roupa | E13: =SUMIFS(Tratamento!H:H,Tratamento!E:E,D13) -> 13830.06 | I13: Air Fryer | J13: 378.8
B14: Qual a % de metas atingidas?
B15: =COUNTIFS(I3:I8,"Sim")/COUNTA(I3:I8) -> 0.5 | D15: Produto | E15: Faturamento | I15: Categoria "Roupa" | J15: Preços
D16: Cama | E16: =SUMIFS(Tratamento!H:H,Tratamento!D:D,D16) -> 32046 | I16: Camisa | J16: 79.9
D17: Geladeira | E17: =SUMIFS(Tratamento!H:H,Tratamento!D:D,D17) -> 30582 | I17: Bermuda | J17: 54.99
D18: Guarda-roupa | E18: =SUMIFS(Tratamento!H:H,Tratamento!D:D,D18) -> 15742.98 | I18: Calça | J18: 107.3
D19: Air Fryer | E19: =SUMIFS(Tratamento!H:H,Tratamento!D:D,D19) -> 9848.8 | I19: Moletom | J19: 297.5
D20: Escrivaninha | E20: =SUMIFS(Tratamento!H:H,Tratamento!D:D,D20) -> 8726.4
D21: Moletom | E21: =SUMIFS(Tratamento!H:H,Tratamento!D:D,D21) -> 8330 | I21: Categoria "Casa" | J21: Preços
D22: Microondas | E22: =SUMIFS(Tratamento!H:H,Tratamento!D:D,D22) -> 8134.44 | I22: Cama | J22: 2289
D23: Camisa | E23: =SUMIFS(Tratamento!H:H,Tratamento!D:D,D23) -> 2476.9 | I23: Guarda-roupa | J23: 1749.22
D24: Calça | E24: =SUMIFS(Tratamento!H:H,Tratamento!D:D,D24) -> 2253.3 | I24: Escrivaninha | J24: 1090.8
D25: Bermuda | E25: =SUMIFS(Tratamento!H:H,Tratamento!D:D,D25) -> 769.86

Sheet Dashboard
